razer_cli/__init__.py
razer_cli/razer_cli/__init__.py
razer_cli/razer_cli/main.py
razer_cli/razer_cli/rc.py
razer_cli/razer_cli/settings.py
razer_cli/razer_cli/util.py
razer_cli/razer_cli/handler/__init__.py
razer_cli/razer_cli/handler/brightness_handler.py
razer_cli/razer_cli/handler/color_effect_handler.py
razer_cli/razer_cli/handler/handler.py
razer_cli/razer_cli/handler/version_handler.py
razer_cli/razer_cli/lister/__init__.py
razer_cli/razer_cli/lister/device_lister.py
razer_cli/razer_cli/lister/lister.py
razer_cli/razer_cli/man_pages/automatic
razer_cli/razer_cli/man_pages/battery
razer_cli/razer_cli/man_pages/brightness
razer_cli/razer_cli/man_pages/color
razer_cli/razer_cli/man_pages/device
razer_cli/razer_cli/man_pages/dpi
razer_cli/razer_cli/man_pages/effect
razer_cli/razer_cli/man_pages/example
razer_cli/razer_cli/man_pages/list_devices
razer_cli/razer_cli/man_pages/poll
razer_cli/razer_cli/man_pages/zone
razer_cli/razer_cli/parser/__init__.py
razer_cli/razer_cli/parser/argument_parser.py
razer_cli/razer_cli/parser/color_parser.py
razer_cli/razer_cli/parser/zone_parser.py
razer_cli/razer_cli/setter/__init__.py
razer_cli/razer_cli/setter/battery_setter.py
razer_cli/razer_cli/setter/brightness_setter.py
razer_cli/razer_cli/setter/color_effect_setter.py
razer_cli/razer_cli/setter/dpi_setter.py
razer_cli/razer_cli/setter/poll_rate_setter.py
razer_cli/razer_cli/setter/resetter.py
razer_cli/razer_cli/setter/setter.py
razer_cli/tests/__init__.py
razer_cli/tests/test_argument_parser.py
razer_cli/tests/test_util.py
razer_cli-2.3.0.dist-info/licenses/LICENSE
razer_cli-2.3.0.dist-info/METADATA
razer_cli-2.3.0.dist-info/WHEEL
razer_cli-2.3.0.dist-info/entry_points.txt
razer_cli-2.3.0.dist-info/top_level.txt
razer_cli-2.3.0.dist-info/RECORD
