Metadata-Version: 2.4
Name: razer-cli
Version: 2.3.0
Summary: Control Razer devices from the command line
Home-page: https://github.com/lolei/razer-cli
Author: Lorenz Leitner
Author-email: lrnz.ltnr@gmail.com
Classifier: License :: OSI Approved :: GNU General Public License v3 (GPLv3)
Classifier: Operating System :: POSIX :: Linux
Classifier: Programming Language :: Python :: 3.6
Requires-Python: >=3.6
License-File: LICENSE
Dynamic: author
Dynamic: author-email
Dynamic: classifier
Dynamic: description
Dynamic: description-content-type
Dynamic: home-page
Dynamic: license-file
Dynamic: requires-python
Dynamic: summary
